segmind/__init__.py
segmind/accounts.py
segmind/client.py
segmind/exceptions.py
segmind/files.py
segmind/finetune.py
segmind/generations.py
segmind/models.py
segmind/pixelflows.py
segmind/resource.py
segmind/webhooks.py
segmind-1.0.0.dist-info/METADATA
segmind-1.0.0.dist-info/WHEEL
segmind-1.0.0.dist-info/licenses/LICENSE
segmind-1.0.0.dist-info/RECORD
